README.txt
setup.cfg
setup.py
Products/__init__.py
Products.AnonymousCommenting.egg-info/PKG-INFO
Products.AnonymousCommenting.egg-info/SOURCES.txt
Products.AnonymousCommenting.egg-info/dependency_links.txt
Products.AnonymousCommenting.egg-info/entry_points.txt
Products.AnonymousCommenting.egg-info/namespace_packages.txt
Products.AnonymousCommenting.egg-info/not-zip-safe
Products.AnonymousCommenting.egg-info/paster_plugins.txt
Products.AnonymousCommenting.egg-info/requires.txt
Products.AnonymousCommenting.egg-info/top_level.txt
Products/AnonymousCommenting/HISTORY.txt
Products/AnonymousCommenting/README.txt
Products/AnonymousCommenting/__init__.py
Products/AnonymousCommenting/configure.zcml
Products/AnonymousCommenting/profiles.zcml
Products/AnonymousCommenting/version.txt
Products/AnonymousCommenting/Extensions/Install.py
Products/AnonymousCommenting/Extensions/__init__.py
Products/AnonymousCommenting/profiles/default/metadata.xml
Products/AnonymousCommenting/profiles/default/rolemap.xml
Products/AnonymousCommenting/profiles/default/skins.xml
Products/AnonymousCommenting/profiles/uninstall/rolemap.xml
Products/AnonymousCommenting/profiles/uninstall/skins.xml
Products/AnonymousCommenting/skins/AnonymousCommenting/discussion_reply.cpy
Products/AnonymousCommenting/skins/AnonymousCommenting/discussion_reply_form.cpt
Products/AnonymousCommenting/skins/AnonymousCommenting/discussion_reply_form.cpt.metadata
Products/AnonymousCommenting/tests/__init__.py
Products/AnonymousCommenting/tests/base.py
Products/AnonymousCommenting/tests/test_anonymousCommenting.py