Metadata-Version: 1.0
Name: Products.AnonymousCommenting
Version: 1.0
Summary: Implements anonymous commenting within a Plone site
Home-page: http://weblion.psu.edu
Author: WebLion Group, Penn State University
Author-email: support@weblion.psu.edu
License: GPL
Platform: UNKNOWN
Classifier: Topic :: Software Development :: Libraries :: Python Modules
Classifier: Framework :: Plone
Classifier: Framework :: Zope2
Classifier: Programming Language :: Python :: 2.4
